brazilian/__init__.py
brazilian/documents/__init__.py
brazilian/documents/cep.py
brazilian/documents/cnh.py
brazilian/documents/cnpj.py
brazilian/documents/cpf.py
brazilian/documents/crm.py
brazilian/errors/invalid_cep_error.py
brazilian/errors/invalid_cnh_error.py
brazilian/errors/invalid_cnpj_error.py
brazilian/errors/invalid_cpf_error.py
brazilian/errors/invalid_crm_error.py
brazilian/errors/invalid_date_error.py
brazilian/errors/invalid_time_error.py
brazilian/pydantic/__init__.py
brazilian/pydantic/cep_model.py
brazilian/pydantic/cnh_model.py
brazilian/pydantic/cnpj_model.py
brazilian/pydantic/cpf_model.py
brazilian/pydantic/crm_model.py
brazilian/pydantic/date_model.py
brazilian/pydantic/time_model.py
brazilian/sqlalchemy/__init__.py
brazilian/sqlalchemy/cep_type.py
brazilian/sqlalchemy/cnh_type.py
brazilian/sqlalchemy/cnpj_type.py
brazilian/sqlalchemy/cpf_type.py
brazilian/sqlalchemy/crm_type.py
brazilian/sqlalchemy/date_type.py
brazilian/sqlalchemy/time_type.py
brazilian/utils/brazilian_date.py
brazilian/utils/brazilian_time.py
brazilian-1.2.0.dist-info/licenses/LICENSE
brazilian-1.2.0.dist-info/METADATA
brazilian-1.2.0.dist-info/WHEEL
brazilian-1.2.0.dist-info/top_level.txt
brazilian-1.2.0.dist-info/RECORD
