Metadata-Version: 2.4
Name: brazilian
Version: 1.2.0
Summary: A complete library about faking / validating brazilian common data
Author-email: Maurício Reisdoefer Pereira <mauricio.reisdoefer2009@gmail.com>
License:                           MIT License
Project-URL: Homepage, https://github.com/MauricioReisdoefer/brazilian
Project-URL: Documentation, https://github.com/MauricioReisdoefer/brazilian/tree/main/docs
Project-URL: Repository, https://github.com/MauricioReisdoefer/brazilian
Project-URL: Issues, https://github.com/MauricioReisdoefer/brazilian/issues
Classifier: Programming Language :: Python :: 3
Classifier: Programming Language :: Python :: 3.9
Classifier: Programming Language :: Python :: 3.10
Classifier: Programming Language :: Python :: 3.11
Classifier: Programming Language :: Python :: 3.12
Classifier: License :: OSI Approved :: GNU General Public License v3 (GPLv3)
Classifier: Operating System :: OS Independent
Requires-Python: >=3.9
License-File: LICENSE
Requires-Dist: requests
Provides-Extra: test
Requires-Dist: pytest; extra == "test"
Requires-Dist: pytest-cov; extra == "test"
Provides-Extra: pydantic
Requires-Dist: pydantic>=2.0; extra == "pydantic"
Provides-Extra: sqlalchemy
Requires-Dist: sqlalchemy>=2.0; extra == "sqlalchemy"
Provides-Extra: orm
Requires-Dist: pydantic>=2.0; extra == "orm"
Requires-Dist: sqlalchemy>=2.0; extra == "orm"
Provides-Extra: all
Requires-Dist: pytest; extra == "all"
Requires-Dist: pytest-cov; extra == "all"
Requires-Dist: pydantic>=2.0; extra == "all"
Requires-Dist: sqlalchemy>=2.0; extra == "all"
Dynamic: license-file
